econtools/__init__.py
econtools/py.typed
econtools/geo/__init__.py
econtools/geo/krig.py
econtools/metrics/__init__.py
econtools/metrics/api.py
econtools/metrics/core.py
econtools/metrics/locallinear.py
econtools/metrics/regutil.py
econtools/metrics/results.py
econtools/metrics/tests/__init__.py
econtools/metrics/tests/test_areg.py
econtools/metrics/tests/test_atsls.py
econtools/metrics/tests/test_colinear.py
econtools/metrics/tests/test_coremethods.py
econtools/metrics/tests/test_liml.py
econtools/metrics/tests/test_ols.py
econtools/metrics/tests/test_savemem.py
econtools/metrics/tests/test_shac.py
econtools/metrics/tests/test_tsls.py
econtools/metrics/tests/data/__init__.py
econtools/metrics/tests/data/auto.dta
econtools/metrics/tests/data/nlswork.dta
econtools/metrics/tests/data/src_areg.py
econtools/metrics/tests/data/src_atsls.py
econtools/metrics/tests/data/src_liml.py
econtools/metrics/tests/data/src_ols.py
econtools/metrics/tests/data/src_tsls.py
econtools/metrics/util/__init__.py
econtools/metrics/util/rand_df.py
econtools/metrics/util/testing.py
econtools/util/__init__.py
econtools/util/frametools.py
econtools/util/gentools.py
econtools/util/io.py
econtools/util/plot.py
econtools/util/reference.py
econtools/util/to_latex.py
econtools/util/tests/__init__.py
econtools/util/tests/test_frametools.py
econtools/util/tests/test_gentools.py
econtools/util/tests/test_io.py
econtools/util/tests/test_to_latex.py
econtools-0.3.2.dist-info/LICENSE.txt
econtools-0.3.2.dist-info/METADATA
econtools-0.3.2.dist-info/WHEEL
econtools-0.3.2.dist-info/top_level.txt
econtools-0.3.2.dist-info/RECORD
