Metadata-Version: 2.1
Name: econtools
Version: 0.3.2
Summary: Econometrics and other tools
Home-page: http://www.danielmsullivan.com/econtools
Author: Daniel M. Sullivan
License: BSD
Platform: UNKNOWN
Classifier: Development Status :: 4 - Beta
Classifier: License :: OSI Approved :: BSD License
Classifier: Topic :: Scientific/Engineering :: Mathematics
Classifier: Topic :: Sociology
Classifier: Topic :: Scientific/Engineering :: Information Analysis
Classifier: Programming Language :: Python :: 3
Classifier: Programming Language :: Python :: 3.6
Classifier: Programming Language :: Python :: 3.7
Classifier: Programming Language :: Python :: 3.8
Classifier: Operating System :: OS Independent
Requires-Python: >=3.6
Requires-Dist: pandas (>=0.16.0)
Requires-Dist: numpy (>=1.9.2)
Requires-Dist: scipy
